<?xml version="1.0" encoding="UTF-8"?>
<!--

  Copyright 2022 Aidan Case

  GtkSourceView is free software; you can redistribute it and/or
  modify it under the terms of the GNU Lesser General Public
  License as published by the Free Software Foundation; either
  version 2.1 of the License, or (at your option) any later version.

  GtkSourceView is distributed in the hope that it will be useful,
  but WITHOUT ANY WARRANTY; without even the implied warranty of
  MERCHANTABILITY or FITNESS FOR A PARTICULAR PURPOSE.  See the GNU
  Lesser General Public License for more details.

  You should have received a copy of the GNU Lesser General Public License
  along with this library; if not, see <http://www.gnu.org/licenses/>.

-->
<style-scheme id="edge" _name="Edge" version="1.0">
  <author>Aidan Case</author>
  <_description>Dark color scheme, based on the vim color scheme of the same name by sainnhe on github</_description>

  <metadata>
    <property name="variant">dark</property>
  </metadata>

  <!-- Named Colors -->
  <color name="bg0"                          value="#2C2E34"/>
  <color name="bg1"                          value="#33353F"/>
  <color name="bg2"                          value="#363944"/>
  <color name="bg3"                          value="#3B3E48"/>
  <color name="bg4"                          value="#414550"/>
  <color name="bg_blue"                      value="#6CB6EB"/>
  <color name="bg_green"                     value="#A0C980"/>
  <color name="bg_grey"                      value="#828A98"/>
  <color name="bg_purple"                    value="#D38AEA"/>
  <color name="bg_red"                       value="#EC7279"/>
  <color name="black"                        value="#202023"/>
  <color name="blue"                         value="#6CB6EB"/>
  <color name="cyan"                         value="#5DBBC1"/>
  <color name="diff_blue"                    value="#354157"/>
  <color name="diff_green"                   value="#7AB34F"/>
  <color name="diff_red"                     value="#8C2B39"/>
  <color name="diff_yellow"                  value="#8F8B14"/>
  <color name="fg"                           value="#C5CDD9"/>
  <color name="green"                        value="#A0C980"/>
  <color name="grey"                         value="#7F8490"/>
  <color name="grey_dim"                     value="#5B616E"/>
  <color name="purple"                       value="#D38AEA"/>
  <color name="red"                          value="#EC7279"/>
  <color name="yellow"                       value="#DEB974"/>

  <!-- Global Styles -->
  <style name="background-pattern"           background="bg_grey"/>
  <style name="bracket-match"                foreground="fg" bold="true"/>
  <style name="bracket-mismatch"             foreground="purple" bold="true"/>
  <style name="current-line"                 background="bg1"/>
  <style name="current-line-number"          background="grey"/>
  <style name="cursor"                       foreground="fg"/>
  <style name="draw-spaces"                  foreground="bg4"/>
  <style name="line-numbers"                 background="bg0" foreground="grey"/>
  <style name="line-numbers-border"          background="#rgba(0,0,0,0)"/>
  <style name="map-overlay"                  background="#rgba(136,138,133,0.25)"/>
  <style name="misspelled-match"             background="blue" foreground="black"/>
  <style name="quick-highlight-match"        background="#rgba(160,201,128,0.25)"/>
  <style name="right-margin"                 background="bg4" foreground="bg4"/>
  <style name="search-match"                 background="green" foreground="bg0"/>
  <style name="search-shadow"                background="#rgba(0,0,0,0.4)"/>
  <style name="selection"                    background="bg3"/>
  <style name="snippet-focus"                bold="false"/>
  <style name="text"                         background="bg0" foreground="fg"/>

  <!-- Defaults -->
  <style name="def:boolean"                  foreground="green"/>
  <style name="def:character"                foreground="green"/>
  <style name="def:comment"                  foreground="grey" italic="true"/>
  <style name="def:constant"                 foreground="yellow" italic="true"/>
  <style name="def:deletion"                 strikethrough="true"/>
  <style name="def:doc-comment-element"      foreground="green"/>
  <style name="def:emphasis"                 italic="true"/>
  <style name="def:enum-name"                foreground="yellow"/>
  <style name="def:error"                    background="diff_red" bold="true"/>
  <style name="def:floating-point"           foreground="green"/>
  <style name="def:function"                 foreground="blue"/>
  <style name="def:heading"                  foreground="purple" bold="true"/>
  <style name="def:identifier"               foreground="cyan" italic="true"/>
  <style name="def:inline-code"              foreground="green"/>
  <style name="def:insertion"                underline="single"/>
  <style name="def:keyword"                  foreground="purple"/>
  <style name="def:link-destination"         foreground="green" italic="true" underline="single"/>
  <style name="def:link-symbol"              foreground="purple"/>
  <style name="def:link-text"                foreground="grey" underline="single"/>
  <style name="def:list-marker"              foreground="red"/>
  <style name="def:macro-name"               foreground="yellow"/>
  <style name="def:net-address"              italic="true" underline="single"/>
  <style name="def:note"                     background="diff_blue" bold="true"/>
  <style name="def:preformatted-section"     foreground="yellow"/>
  <style name="def:preprocessor"             foreground="purple"/>
  <style name="def:shebang"                  foreground="purple"/>
  <style name="def:special-char"             foreground="yellow"/>
  <style name="def:special-constant"         foreground="cyan" italic="true"/>
  <style name="def:statement"                foreground="purple"/>
  <style name="def:string"                   foreground="green"/>
  <style name="def:strong-emphasis"          bold="true"/>
  <style name="def:thematic-break"           foreground="grey" bold="true"/>
  <style name="def:type"                     foreground="red"/>
  <style name="def:warning"                  background="diff_yellow"/>
  <style name="action::hover-definition"     background="bg4" underline="single"/>

  <!-- C -->
  <style name="c:storage-class"              foreground="purple"/>
  <style name="c:type-keyword"               foreground="red" italic="true"/>
  <style name="debugger::breakpoint"         background="red" foreground="bg0"/>
  <style name="debugger::current-breakpoint" background="diff_red" foreground="bg0"/>
  <style name="diagnostician::deprecated"    underline="error" underline-color="fg"/>
  <style name="diagnostician::error"         underline="error" underline-color="red"/>
  <style name="diagnostician::note"          underline="error" underline-color="blue"/>
  <style name="diagnostician::unused"        underline="error" underline-color="grey"/>
  <style name="diagnostician::warning"       underline="error" underline-color="yellow"/>

  <!-- Diff -->
  <style name="diff:added-line"              foreground="diff_green"/>
  <style name="diff:changed-line"            foreground="diff_yellow"/>
  <style name="diff:diff-file"               foreground="fg"/>
  <style name="diff:location"                foreground="diff_blue"/>
  <style name="diff:removed-line"            foreground="diff_red"/>
  <style name="diff:special-case"            foreground="fg"/>

  <!-- gtk-doc -->
  <style name="gtk-doc:constant"             bold="true"/>
  <style name="gtk-doc:deprecated"           bold="true"/>
  <style name="gtk-doc:function"             bold="true"/>
  <style name="gtk-doc:function-name"        bold="true"/>
  <style name="gtk-doc:parameter"            bold="true"/>
  <style name="gtk-doc:property-name"        bold="true"/>
  <style name="gtk-doc:return"               bold="true"/>
  <style name="gtk-doc:signal-name"          bold="true"/>
  <style name="gtk-doc:since"                bold="true"/>
  <style name="gtk-doc:type"                 bold="true"/>
  <style name="gutter:added-line"            use-style="diff:added-line"/>
  <style name="gutter:changed-line"          use-style="diff:changed-line"/>
  <style name="gutter:removed-line"          use-style="diff:removed-line"/>

  <!-- Java -->
  <style name="java:memory"                  foreground="purple"/>
  <style name="java:null-value"              foreground="yellow" italic="true"/>
  <style name="java:scope-declaration"       foreground="purple"/>
  <style name="java:type"                    foreground="red" italic="true"/>

  <!-- JavaScript -->
  <style name="js:built-in-constructor"      foreground="cyan"/>
  <style name="js:built-in-function"         foreground="blue"/>
  <style name="js:template-literal"          foreground="yellow"/>

  <!-- Rust -->
  <style name="rust:attribute"               foreground="yellow"/>
  <style name="rust:lifetime"                foreground="yellow"/>
  <style name="rust:macro"                   foreground="cyan" italic="true"/>
  <style name="rust:number"                  foreground="green"/>
  <style name="rust:scope"                   foreground="red" italic="true"/>

  <!-- Java -->
  <style name="java:storage-class"           use-style="java:type"/>

  <!-- JavaScript -->
  <style name="js:built-in-method"           foreground="cyan" italic="true"/>

  <!-- LaTeX -->
  <style name="latex:command"                foreground="red"/>

  <!-- Java -->
  <style name="java:declaration"             use-style="java:type"/>

  <!-- Rust -->
  <style name="rust:type"                    foreground="red" italic="true"/>

  <!-- XML -->
  <style name="xml:cdata-delim"              foreground="grey"/>
  <style name="xml:doctype"                  foreground="grey"/>
  <style name="xml:tag"                      foreground="purple"/>

</style-scheme>